README.md
setup.py
res_birdnet/__init__.py
res_birdnet/models.py
res_birdnet.egg-info/PKG-INFO
res_birdnet.egg-info/SOURCES.txt
res_birdnet.egg-info/dependency_links.txt
res_birdnet.egg-info/requires.txt
res_birdnet.egg-info/top_level.txt